Metadata-Version: 2.4
Name: ebird-api-requests
Version: 4.0.2
Summary: A python library for accessing the eBird API, version 2.0
Author-email: Stuart MacKay <smackay@flagstonesoftware.com>
License: MIT License
Project-URL: Repository, https://github.com/StuartMacKay/ebird-api-requests.git
Project-URL: Issues, https://github.com/StuartMacKay/ebird-api-requests/issues
Project-URL: Changelog, https://github.com/StuartMacKay/ebird-api-requests/blob/master/CHANGELOG.md
Keywords: eBird,API,client
Classifier: Development Status :: 5 - Production/Stable
Classifier: Environment :: Console
Classifier: Intended Audience :: Science/Research
Classifier: License :: OSI Approved :: MIT License
Classifier: Operating System :: OS Independent
Classifier: Programming Language :: Python
Classifier: Programming Language :: Python :: 3
Classifier: Programming Language :: Python :: 3.10
Classifier: Programming Language :: Python :: 3.11
Classifier: Programming Language :: Python :: 3.12
Classifier: Programming Language :: Python :: 3.13
Classifier: Programming Language :: Python :: Implementation :: CPython
Classifier: Natural Language :: English
Classifier: Topic :: Utilities
Classifier: Topic :: Internet
Requires-Python: >=3.10
License-File: LICENSE.txt
Dynamic: license-file
